simple_ans/EncodedSignal.py
simple_ans/__init__.py
simple_ans/_simple_ans.cpython-313-x86_64-linux-gnu.so
simple_ans/choose_symbol_counts.py
simple_ans/encode_decode.py
simple_ans/cpp/libdivide.h
simple_ans/cpp/simple_ans.cpp
simple_ans/cpp/simple_ans.hpp
simple_ans/pure_python/__init__.py
simple_ans/pure_python/py_encode_decode.py
simple_ans-0.3.1.dist-info/METADATA
simple_ans-0.3.1.dist-info/WHEEL
simple_ans-0.3.1.dist-info/RECORD
simple_ans-0.3.1.dist-info/licenses/LICENSE
