Metadata-Version: 2.2
Name: simple_ans
Version: 0.3.1
Summary: Simple ANS (Asymmetric Numeral Systems) implementation
Author-Email: Jeremy Magland <jmagland@flatironinstitute.org>
Classifier: Development Status :: 3 - Alpha
Classifier: Intended Audience :: Developers
Classifier: License :: OSI Approved :: Apache Software License
Classifier: Programming Language :: Python :: 3
Classifier: Programming Language :: Python :: 3.9
Classifier: Programming Language :: Python :: 3.10
Classifier: Programming Language :: Python :: 3.11
Classifier: Programming Language :: Python :: 3.12
Classifier: Programming Language :: Python :: 3.13
Classifier: Topic :: Scientific/Engineering
Requires-Python: >=3.8
Requires-Dist: numpy>=1.21.0
Provides-Extra: test
Requires-Dist: pytest; extra == "test"
Provides-Extra: benchmark
Requires-Dist: matplotlib; extra == "benchmark"
Requires-Dist: zstandard; extra == "benchmark"
Requires-Dist: blosc2; extra == "benchmark"
